lemma_from_wiki/__init__.py
lemma_from_wiki/__main__.py
lemma_from_wiki/cli_utils.py
lemma_from_wiki/command_runner.py
lemma_from_wiki/config.py
lemma_from_wiki/generate_lemma_file.py
lemma_from_wiki/help_text.py
lemma_from_wiki/lemma_utils.py
lemma_from_wiki/main.py
lemma_from_wiki/utils.py
lemma_from_wiki-0.2.0.dist-info/METADATA
lemma_from_wiki-0.2.0.dist-info/WHEEL
lemma_from_wiki-0.2.0.dist-info/entry_points.txt
lemma_from_wiki-0.2.0.dist-info/licenses/LICENSE
lemma_from_wiki-0.2.0.dist-info/RECORD
