Metadata-Version: 2.3
Name: lemma-from-wiki
Version: 0.2.0
Summary: Generates lemma files for vocabsieve
Author-email: Jonathan Fox <32023524+jonathanfox5@users.noreply.github.com>
Classifier: Intended Audience :: Developers
Classifier: License :: OSI Approved :: GNU Affero General Public License v3 or later (AGPLv3+)
Classifier: Operating System :: OS Independent
Classifier: Programming Language :: Python :: 3
Classifier: Programming Language :: Python :: 3.10
Classifier: Programming Language :: Python :: 3.11
Classifier: Programming Language :: Python :: 3.12
Classifier: Topic :: Education
Classifier: Topic :: Text Processing :: Linguistic
Requires-Python: <3.13,>=3.12
Requires-Dist: datasets<4.0.0,>=3.1.0
Requires-Dist: lemon-tizer<1.0.0,>=0.0.7
Requires-Dist: numpy<2
Requires-Dist: pandas<3.0.0,>=2.2.3
Requires-Dist: pip
Requires-Dist: regex>=2024.11.6
Requires-Dist: simplemma<2.0.0,>=1.1.2
Requires-Dist: spacy[cuda12x]==3.7.5
Requires-Dist: typer<1.0.0,>=0.13.1
